{"item":[{"type":"GROUP","linkId":"name","required":false,"item":[{"type":"STRING","required":true,"linkId":"1","text":"Organization Name","fieldName":"organizationName"},{"type":"TEXT","required":false,"linkId":"description","text":"Description","fieldName":"description"},{"type":"TEXT","required":false,"linkId":"contact","text":"Contact Information","fieldName":"contactInformation"},{"type":"BOOLEAN","required":false,"hidden":false,"text":"Victim Service Provider","linkId":"victimServiceProvider","fieldName":"victimServiceProvider"}]}]}